<?xml version="1.0" encoding="utf-8" ?>
<c2layout>
    <name>menu layout</name>
    <sid>5687686032195995</sid>
    <event-sheet>menu ES</event-sheet>
    <size>
        <width>1920</width>
        <height>1080</height>
    </size>
    <margins>
        <horizontal>500</horizontal>
        <vertical>500</vertical>
    </margins>
    <unbounded-scrolling>0</unbounded-scrolling>
    <layers>
        <layer name="Layer 0" sid="3658551978260519">
            <initially-visible>1</initially-visible>
            <background-color>255,255,255</background-color>
            <transparent>0</transparent>
            <parallax>
                <x>1</x>
                <y>1</y>
            </parallax>
            <zoom-rate>1</zoom-rate>
            <opacity>1</opacity>
            <force-own-texture>0</force-own-texture>
            <global>0</global>
            <use-render-cells>0</use-render-cells>
            <blend-mode>0</blend-mode>
            <effect-fallback>0</effect-fallback>
            <instances>
                <instance type="Sprite2" uid="59">
                    <properties>
                        <initial-visibility>Visible</initial-visibility>
                        <initial-animation>Default</initial-animation>
                        <initial-frame>0</initial-frame>
                        <collisions>Enabled</collisions>
                    </properties>
                    <blend-mode>0</blend-mode>
                    <effect-fallback>0</effect-fallback>
                    <world>
                        <x>960</x>
                        <y>540</y>
                        <z>0</z>
                        <width>1980</width>
                        <height>1290</height>
                        <depth>0</depth>
                        <hotspotX>0.5</hotspotX>
                        <hotspotY>0.5</hotspotY>
                        <angle>0</angle>
                        <opacity>1</opacity>
                    </world>
                </instance>
                <instance type="menubar" uid="68">
                    <properties>
                        <initial-visibility>Visible</initial-visibility>
                        <initial-animation>Default</initial-animation>
                        <initial-frame>0</initial-frame>
                        <collisions>Disabled</collisions>
                    </properties>
                    <behavior-instances>
                        <behavior-instance type="Solid">
                            <properties>
                                <initial-state>Enabled</initial-state>
                            </properties>
                        </behavior-instance>
                    </behavior-instances>
                    <blend-mode>0</blend-mode>
                    <effect-fallback>0</effect-fallback>
                    <world>
                        <x>832</x>
                        <y>-384</y>
                        <z>0</z>
                        <width>608</width>
                        <height>-32</height>
                        <depth>0</depth>
                        <hotspotX>0.5</hotspotX>
                        <hotspotY>0.5</hotspotY>
                        <angle>0</angle>
                        <opacity>1</opacity>
                    </world>
                </instance>
                <instance type="TextBox" uid="49">
                    <properties>
                        <text></text>
                        <placeholder>NAME</placeholder>
                        <tooltip></tooltip>
                        <initial-visibility>Visible</initial-visibility>
                        <enabled>Yes</enabled>
                        <read-only>No</read-only>
                        <spell-check>No</spell-check>
                        <type>Text</type>
                        <auto-font-size>No</auto-font-size>
                        <id-optional></id-optional>
                    </properties>
                    <blend-mode>0</blend-mode>
                    <effect-fallback>0</effect-fallback>
                    <world>
                        <x>-1120</x>
                        <y>352</y>
                        <z>0</z>
                        <width>350</width>
                        <height>80</height>
                        <depth>0</depth>
                        <hotspotX>0</hotspotX>
                        <hotspotY>0</hotspotY>
                    </world>
                </instance>
                <instance type="b3" uid="37">
                    <properties>
                        <initial-visibility>Visible</initial-visibility>
                        <initial-animation>Default</initial-animation>
                        <initial-frame>0</initial-frame>
                        <collisions>Enabled</collisions>
                    </properties>
                    <behavior-instances>
                        <behavior-instance type="Pin" />
                        <behavior-instance type="LiteTween">
                            <properties>
                                <active-on-start>No</active-on-start>
                                <tweened-property>Angle</tweened-property>
                                <function>Linear</function>
                                <target>180</target>
                                <target-mode>Absolute</target-mode>
                                <duration>5</duration>
                                <enforce-mode>Enforce</enforce-mode>
                            </properties>
                        </behavior-instance>
                    </behavior-instances>
                    <blend-mode>0</blend-mode>
                    <effect-fallback>0</effect-fallback>
                    <world>
                        <x>-352</x>
                        <y>896</y>
                        <z>0</z>
                        <width>180</width>
                        <height>180</height>
                        <depth>0</depth>
                        <hotspotX>0.5</hotspotX>
                        <hotspotY>0.5</hotspotY>
                        <angle>0</angle>
                        <opacity>1</opacity>
                    </world>
                </instance>
                <instance type="levels" uid="62">
                    <properties>
                        <text>3</text>
                        <initial-visibility>Visible</initial-visibility>
                        <font>Arial,-24,400,0</font>
                        <color>255,255,255</color>
                        <horizontal-alignment>Center</horizontal-alignment>
                        <vertical-alignment>Center</vertical-alignment>
                        <hotspot>Top-left</hotspot>
                        <wrapping>Word</wrapping>
                        <line-height>0</line-height>
                    </properties>
                    <blend-mode>0</blend-mode>
                    <effect-fallback>0</effect-fallback>
                    <world>
                        <x>-288</x>
                        <y>640</y>
                        <z>0</z>
                        <width>83</width>
                        <height>107</height>
                        <depth>0</depth>
                        <hotspotX>0</hotspotX>
                        <hotspotY>0</hotspotY>
                        <angle>0</angle>
                        <opacity>1</opacity>
                    </world>
                </instance>
                <instance type="Title" uid="7">
                    <properties>
                        <initial-visibility>Visible</initial-visibility>
                        <initial-animation>Default</initial-animation>
                        <initial-frame>0</initial-frame>
                        <collisions>Enabled</collisions>
                    </properties>
                    <behavior-instances>
                        <behavior-instance type="Flash" />
                    </behavior-instances>
                    <blend-mode>0</blend-mode>
                    <effect-fallback>0</effect-fallback>
                    <world>
                        <x>982</x>
                        <y>367</y>
                        <z>0</z>
                        <width>1522</width>
                        <height>186</height>
                        <depth>0</depth>
                        <hotspotX>0.500539362</hotspotX>
                        <hotspotY>0.504950523</hotspotY>
                        <angle>0</angle>
                        <opacity>1</opacity>
                    </world>
                </instance>
                <instance type="SliderGrowthSpeed" uid="74">
                    <properties>
                        <value>5</value>
                        <minimum>1</minimum>
                        <maximum>10</maximum>
                        <step>0.1</step>
                        <tooltip>Growth Speed</tooltip>
                        <initial-visibility>Visible</initial-visibility>
                        <enabled>Yes</enabled>
                        <id-optional></id-optional>
                    </properties>
                    <blend-mode>0</blend-mode>
                    <effect-fallback>0</effect-fallback>
                    <world>
                        <x>2048</x>
                        <y>352</y>
                        <z>0</z>
                        <width>215</width>
                        <height>30</height>
                        <depth>0</depth>
                        <hotspotX>0</hotspotX>
                        <hotspotY>0</hotspotY>
                    </world>
                </instance>
                <instance type="Game" uid="27">
                    <properties>
                        <type>Button</type>
                        <text>START</text>
                        <tooltip></tooltip>
                        <initial-visibility>Visible</initial-visibility>
                        <enabled>Yes</enabled>
                        <auto-font-size>Yes</auto-font-size>
                        <id-optional></id-optional>
                        <checked>No</checked>
                    </properties>
                    <blend-mode>0</blend-mode>
                    <effect-fallback>0</effect-fallback>
                    <world>
                        <x>-928</x>
                        <y>128</y>
                        <z>0</z>
                        <width>250</width>
                        <height>80</height>
                        <depth>0</depth>
                        <hotspotX>0</hotspotX>
                        <hotspotY>0</hotspotY>
                    </world>
                </instance>
                <instance type="SliderRotateSpeed" uid="28">
                    <properties>
                        <value>0.4</value>
                        <minimum>0.1</minimum>
                        <maximum>1</maximum>
                        <step>0.1</step>
                        <tooltip></tooltip>
                        <initial-visibility>Visible</initial-visibility>
                        <enabled>Yes</enabled>
                        <id-optional></id-optional>
                    </properties>
                    <blend-mode>0</blend-mode>
                    <effect-fallback>0</effect-fallback>
                    <world>
                        <x>2080</x>
                        <y>576</y>
                        <z>0</z>
                        <width>215</width>
                        <height>30</height>
                        <depth>0</depth>
                        <hotspotX>0</hotspotX>
                        <hotspotY>0</hotspotY>
                    </world>
                </instance>
                <instance type="GrowSpeedText" uid="29">
                    <properties>
                        <text>Text</text>
                        <initial-visibility>Visible</initial-visibility>
                        <font>Arial,-40,400,0</font>
                        <color>255,255,255</color>
                        <horizontal-alignment>Left</horizontal-alignment>
                        <vertical-alignment>Top</vertical-alignment>
                        <hotspot>Top-left</hotspot>
                        <wrapping>Word</wrapping>
                        <line-height>0</line-height>
                    </properties>
                    <blend-mode>0</blend-mode>
                    <effect-fallback>0</effect-fallback>
                    <world>
                        <x>1984</x>
                        <y>288</y>
                        <z>0</z>
                        <width>343</width>
                        <height>56</height>
                        <depth>0</depth>
                        <hotspotX>0</hotspotX>
                        <hotspotY>0</hotspotY>
                        <angle>0</angle>
                        <opacity>1</opacity>
                    </world>
                </instance>
                <instance type="SpinSpeed" uid="30">
                    <properties>
                        <text>Text</text>
                        <initial-visibility>Visible</initial-visibility>
                        <font>Arial,-40,400,0</font>
                        <color>255,255,255</color>
                        <horizontal-alignment>Left</horizontal-alignment>
                        <vertical-alignment>Top</vertical-alignment>
                        <hotspot>Top-left</hotspot>
                        <wrapping>Word</wrapping>
                        <line-height>0</line-height>
                    </properties>
                    <blend-mode>0</blend-mode>
                    <effect-fallback>0</effect-fallback>
                    <world>
                        <x>2016</x>
                        <y>480</y>
                        <z>0</z>
                        <width>411</width>
                        <height>58</height>
                        <depth>0</depth>
                        <hotspotX>0</hotspotX>
                        <hotspotY>0</hotspotY>
                        <angle>0</angle>
                        <opacity>1</opacity>
                    </world>
                </instance>
                <instance type="Instructions" uid="33">
                    <properties>
                        <text></text>
                        <initial-visibility>Visible</initial-visibility>
                        <font>Arial,-24,400,0</font>
                        <color>255,255,255</color>
                        <horizontal-alignment>Center</horizontal-alignment>
                        <vertical-alignment>Center</vertical-alignment>
                        <hotspot>Top-left</hotspot>
                        <wrapping>Word</wrapping>
                        <line-height>0</line-height>
                    </properties>
                    <blend-mode>0</blend-mode>
                    <effect-fallback>0</effect-fallback>
                    <world>
                        <x>58</x>
                        <y>694</y>
                        <z>0</z>
                        <width>449</width>
                        <height>420</height>
                        <depth>0</depth>
                        <hotspotX>0</hotspotX>
                        <hotspotY>0</hotspotY>
                        <angle>0</angle>
                        <opacity>1</opacity>
                    </world>
                </instance>
                <instance type="SelectedLevel" uid="34">
                    <properties>
                        <text>Text</text>
                        <initial-visibility>Visible</initial-visibility>
                        <font>Arial,-32,400,0</font>
                        <color>255,255,255</color>
                        <horizontal-alignment>Center</horizontal-alignment>
                        <vertical-alignment>Center</vertical-alignment>
                        <hotspot>Center</hotspot>
                        <wrapping>Word</wrapping>
                        <line-height>0</line-height>
                    </properties>
                    <blend-mode>0</blend-mode>
                    <effect-fallback>0</effect-fallback>
                    <world>
                        <x>288</x>
                        <y>1024</y>
                        <z>0</z>
                        <width>512</width>
                        <height>96</height>
                        <depth>0</depth>
                        <hotspotX>0.5</hotspotX>
                        <hotspotY>0.5</hotspotY>
                        <angle>0</angle>
                        <opacity>1</opacity>
                    </world>
                </instance>
                <instance type="YourHighScore" uid="51">
                    <properties>
                        <text></text>
                        <initial-visibility>Visible</initial-visibility>
                        <font>Arial,-32,400,0</font>
                        <color>255,255,255</color>
                        <horizontal-alignment>Center</horizontal-alignment>
                        <vertical-alignment>Center</vertical-alignment>
                        <hotspot>Center</hotspot>
                        <wrapping>Word</wrapping>
                        <line-height>0</line-height>
                    </properties>
                    <blend-mode>0</blend-mode>
                    <effect-fallback>0</effect-fallback>
                    <world>
                        <x>1056</x>
                        <y>1248</y>
                        <z>0</z>
                        <width>384</width>
                        <height>96</height>
                        <depth>0</depth>
                        <hotspotX>0.5</hotspotX>
                        <hotspotY>0.5</hotspotY>
                        <angle>0</angle>
                        <opacity>1</opacity>
                    </world>
                </instance>
                <instance type="b6locked" uid="52">
                    <properties>
                        <initial-visibility>Visible</initial-visibility>
                        <initial-animation>Default</initial-animation>
                        <initial-frame>0</initial-frame>
                        <collisions>Enabled</collisions>
                    </properties>
                    <behavior-instances>
                        <behavior-instance type="Pin" />
                        <behavior-instance type="LiteTween">
                            <properties>
                                <active-on-start>No</active-on-start>
                                <tweened-property>Position</tweened-property>
                                <function>EaseOutBounce</function>
                                <target>100,100</target>
                                <target-mode>Absolute</target-mode>
                                <duration>2.5</duration>
                                <enforce-mode>Compromise</enforce-mode>
                            </properties>
                        </behavior-instance>
                    </behavior-instances>
                    <blend-mode>0</blend-mode>
                    <effect-fallback>0</effect-fallback>
                    <world>
                        <x>-256</x>
                        <y>224</y>
                        <z>0</z>
                        <width>200</width>
                        <height>200</height>
                        <depth>0</depth>
                        <hotspotX>0.5</hotspotX>
                        <hotspotY>0.5</hotspotY>
                        <angle>0</angle>
                        <opacity>1</opacity>
                    </world>
                </instance>
                <instance type="b8locked" uid="55">
                    <properties>
                        <initial-visibility>Visible</initial-visibility>
                        <initial-animation>Default</initial-animation>
                        <initial-frame>0</initial-frame>
                        <collisions>Enabled</collisions>
                    </properties>
                    <behavior-instances>
                        <behavior-instance type="Pin" />
                        <behavior-instance type="LiteTween">
                            <properties>
                                <active-on-start>No</active-on-start>
                                <tweened-property>Position</tweened-property>
                                <function>EaseOutBounce</function>
                                <target>100,100</target>
                                <target-mode>Absolute</target-mode>
                                <duration>2.5</duration>
                                <enforce-mode>Compromise</enforce-mode>
                            </properties>
                        </behavior-instance>
                    </behavior-instances>
                    <blend-mode>0</blend-mode>
                    <effect-fallback>0</effect-fallback>
                    <world>
                        <x>-288</x>
                        <y>-32</y>
                        <z>0</z>
                        <width>200</width>
                        <height>200</height>
                        <depth>0</depth>
                        <hotspotX>0.5</hotspotX>
                        <hotspotY>0.5</hotspotY>
                        <angle>0</angle>
                        <opacity>1</opacity>
                    </world>
                </instance>
                <instance type="Locked" uid="61">
                    <properties>
                        <text>Clear the previous level to play!</text>
                        <initial-visibility>Visible</initial-visibility>
                        <font>Arial,-19,400,0</font>
                        <color>255,255,255</color>
                        <horizontal-alignment>Center</horizontal-alignment>
                        <vertical-alignment>Center</vertical-alignment>
                        <hotspot>Center</hotspot>
                        <wrapping>Word</wrapping>
                        <line-height>0</line-height>
                    </properties>
                    <blend-mode>0</blend-mode>
                    <effect-fallback>0</effect-fallback>
                    <world>
                        <x>-384</x>
                        <y>544</y>
                        <z>0</z>
                        <width>128</width>
                        <height>128</height>
                        <depth>0</depth>
                        <hotspotX>0.5</hotspotX>
                        <hotspotY>0.5</hotspotY>
                        <angle>0</angle>
                        <opacity>1</opacity>
                    </world>
                </instance>
                <instance type="g4" uid="69">
                    <properties>
                        <initial-visibility>Visible</initial-visibility>
                        <initial-animation>Default</initial-animation>
                        <initial-frame>0</initial-frame>
                        <collisions>Enabled</collisions>
                    </properties>
                    <behavior-instances>
                        <behavior-instance type="Pin" />
                    </behavior-instances>
                    <blend-mode>0</blend-mode>
                    <effect-fallback>0</effect-fallback>
                    <world>
                        <x>-192</x>
                        <y>576</y>
                        <z>0</z>
                        <width>200</width>
                        <height>200</height>
                        <depth>0</depth>
                        <hotspotX>0.5</hotspotX>
                        <hotspotY>0.5</hotspotY>
                        <angle>0</angle>
                        <opacity>1</opacity>
                    </world>
                </instance>
                <instance type="Sprite" uid="70">
                    <properties>
                        <initial-visibility>Visible</initial-visibility>
                        <initial-animation>Default</initial-animation>
                        <initial-frame>0</initial-frame>
                        <collisions>Enabled</collisions>
                    </properties>
                    <blend-mode>0</blend-mode>
                    <effect-fallback>0</effect-fallback>
                    <world>
                        <x>2208</x>
                        <y>160</y>
                        <z>0</z>
                        <width>320</width>
                        <height>240</height>
                        <depth>0</depth>
                        <hotspotX>0.5</hotspotX>
                        <hotspotY>0.5</hotspotY>
                        <angle>0</angle>
                        <opacity>1</opacity>
                    </world>
                </instance>
                <instance type="List" uid="92">
                    <properties>
                        <items>0;1;2;3;</items>
                        <tooltip>Gamepad Number</tooltip>
                        <initial-visibility>Visible</initial-visibility>
                        <enabled>Yes</enabled>
                        <type>Dropdown list</type>
                        <multi-select>No</multi-select>
                        <auto-font-size>Yes</auto-font-size>
                        <id-optional></id-optional>
                    </properties>
                    <blend-mode>0</blend-mode>
                    <effect-fallback>0</effect-fallback>
                    <world>
                        <x>2368</x>
                        <y>-128</y>
                        <z>0</z>
                        <width>160</width>
                        <height>32</height>
                        <depth>0</depth>
                        <hotspotX>0</hotspotX>
                        <hotspotY>0</hotspotY>
                    </world>
                </instance>
                <instance type="Version" uid="93">
                    <properties>
                        <text>Text</text>
                        <initial-visibility>Visible</initial-visibility>
                        <font>Arial,-48,400,0</font>
                        <color>255,255,255</color>
                        <horizontal-alignment>Left</horizontal-alignment>
                        <vertical-alignment>Top</vertical-alignment>
                        <hotspot>Top-left</hotspot>
                        <wrapping>Word</wrapping>
                        <line-height>0</line-height>
                    </properties>
                    <blend-mode>0</blend-mode>
                    <effect-fallback>0</effect-fallback>
                    <world>
                        <x>1580</x>
                        <y>1028</y>
                        <z>0</z>
                        <width>448</width>
                        <height>192</height>
                        <depth>0</depth>
                        <hotspotX>0</hotspotX>
                        <hotspotY>0</hotspotY>
                        <angle>0</angle>
                        <opacity>1</opacity>
                    </world>
                </instance>
                <instance type="GamepadNumber" uid="94">
                    <properties>
                        <text>Gamepad Number:</text>
                        <initial-visibility>Visible</initial-visibility>
                        <font>Arial,-40,400,0</font>
                        <color>255,255,255</color>
                        <horizontal-alignment>Left</horizontal-alignment>
                        <vertical-alignment>Top</vertical-alignment>
                        <hotspot>Top-left</hotspot>
                        <wrapping>Word</wrapping>
                        <line-height>0</line-height>
                    </properties>
                    <blend-mode>0</blend-mode>
                    <effect-fallback>0</effect-fallback>
                    <world>
                        <x>2088</x>
                        <y>-256</y>
                        <z>0</z>
                        <width>416</width>
                        <height>192</height>
                        <depth>0</depth>
                        <hotspotX>0</hotspotX>
                        <hotspotY>0</hotspotY>
                        <angle>0</angle>
                        <opacity>1</opacity>
                    </world>
                </instance>
                <instance type="BankTimeoutSlider" uid="95">
                    <properties>
                        <value>0.4</value>
                        <minimum>0</minimum>
                        <maximum>2</maximum>
                        <step>0.1</step>
                        <tooltip></tooltip>
                        <initial-visibility>Visible</initial-visibility>
                        <enabled>Yes</enabled>
                        <id-optional></id-optional>
                    </properties>
                    <blend-mode>0</blend-mode>
                    <effect-fallback>0</effect-fallback>
                    <world>
                        <x>2720</x>
                        <y>32</y>
                        <z>0</z>
                        <width>200</width>
                        <height>25</height>
                        <depth>0</depth>
                        <hotspotX>0</hotspotX>
                        <hotspotY>0</hotspotY>
                    </world>
                </instance>
                <instance type="CashinTimeoutSlider" uid="96">
                    <properties>
                        <value>0.4</value>
                        <minimum>0</minimum>
                        <maximum>2</maximum>
                        <step>0.1</step>
                        <tooltip></tooltip>
                        <initial-visibility>Visible</initial-visibility>
                        <enabled>Yes</enabled>
                        <id-optional></id-optional>
                    </properties>
                    <blend-mode>0</blend-mode>
                    <effect-fallback>0</effect-fallback>
                    <world>
                        <x>2848</x>
                        <y>288</y>
                        <z>0</z>
                        <width>200</width>
                        <height>25</height>
                        <depth>0</depth>
                        <hotspotX>0</hotspotX>
                        <hotspotY>0</hotspotY>
                    </world>
                </instance>
                <instance type="BankTimeoutText" uid="97">
                    <properties>
                        <text>Bank Timeout</text>
                        <initial-visibility>Visible</initial-visibility>
                        <font>Arial,-40,400,0</font>
                        <color>255,255,255</color>
                        <horizontal-alignment>Left</horizontal-alignment>
                        <vertical-alignment>Top</vertical-alignment>
                        <hotspot>Top-left</hotspot>
                        <wrapping>Word</wrapping>
                        <line-height>0</line-height>
                    </properties>
                    <blend-mode>0</blend-mode>
                    <effect-fallback>0</effect-fallback>
                    <world>
                        <x>2720</x>
                        <y>-96</y>
                        <z>0</z>
                        <width>608</width>
                        <height>320</height>
                        <depth>0</depth>
                        <hotspotX>0</hotspotX>
                        <hotspotY>0</hotspotY>
                        <angle>0</angle>
                        <opacity>1</opacity>
                    </world>
                </instance>
                <instance type="CashTimeoutText" uid="98">
                    <properties>
                        <text>Cash-in Timeout</text>
                        <initial-visibility>Visible</initial-visibility>
                        <font>Arial,-40,400,0</font>
                        <color>255,255,255</color>
                        <horizontal-alignment>Left</horizontal-alignment>
                        <vertical-alignment>Top</vertical-alignment>
                        <hotspot>Top-left</hotspot>
                        <wrapping>Word</wrapping>
                        <line-height>0</line-height>
                    </properties>
                    <blend-mode>0</blend-mode>
                    <effect-fallback>0</effect-fallback>
                    <world>
                        <x>2976</x>
                        <y>160</y>
                        <z>0</z>
                        <width>992</width>
                        <height>896</height>
                        <depth>0</depth>
                        <hotspotX>0</hotspotX>
                        <hotspotY>0</hotspotY>
                        <angle>0</angle>
                        <opacity>1</opacity>
                    </world>
                </instance>
                <instance type="ButtonSettings" uid="100">
                    <properties>
                        <type>Button</type>
                        <text>Settings</text>
                        <tooltip></tooltip>
                        <initial-visibility>Visible</initial-visibility>
                        <enabled>Yes</enabled>
                        <auto-font-size>Yes</auto-font-size>
                        <id-optional></id-optional>
                        <checked>No</checked>
                    </properties>
                    <blend-mode>0</blend-mode>
                    <effect-fallback>0</effect-fallback>
                    <world>
                        <x>2133</x>
                        <y>857</y>
                        <z>0</z>
                        <width>288</width>
                        <height>96</height>
                        <depth>0</depth>
                        <hotspotX>0</hotspotX>
                        <hotspotY>0</hotspotY>
                    </world>
                </instance>
                <instance type="SliderDecayStart" uid="101">
                    <properties>
                        <value>300</value>
                        <minimum>100</minimum>
                        <maximum>500</maximum>
                        <step>25</step>
                        <tooltip></tooltip>
                        <initial-visibility>Visible</initial-visibility>
                        <enabled>Yes</enabled>
                        <id-optional></id-optional>
                    </properties>
                    <blend-mode>0</blend-mode>
                    <effect-fallback>0</effect-fallback>
                    <world>
                        <x>2274</x>
                        <y>1398</y>
                        <z>0</z>
                        <width>224</width>
                        <height>32</height>
                        <depth>0</depth>
                        <hotspotX>0</hotspotX>
                        <hotspotY>0</hotspotY>
                    </world>
                </instance>
                <instance type="SliderDecayRate" uid="102">
                    <properties>
                        <value>10</value>
                        <minimum>0</minimum>
                        <maximum>50</maximum>
                        <step>1</step>
                        <tooltip></tooltip>
                        <initial-visibility>Visible</initial-visibility>
                        <enabled>Yes</enabled>
                        <id-optional></id-optional>
                    </properties>
                    <blend-mode>0</blend-mode>
                    <effect-fallback>0</effect-fallback>
                    <world>
                        <x>39</x>
                        <y>1314</y>
                        <z>0</z>
                        <width>192</width>
                        <height>32</height>
                        <depth>0</depth>
                        <hotspotX>0</hotspotX>
                        <hotspotY>0</hotspotY>
                    </world>
                </instance>
                <instance type="DecayRate" uid="103">
                    <properties>
                        <text>Decay Rate</text>
                        <initial-visibility>Visible</initial-visibility>
                        <font>Arial,-40,400,0</font>
                        <color>255,255,255</color>
                        <horizontal-alignment>Left</horizontal-alignment>
                        <vertical-alignment>Top</vertical-alignment>
                        <hotspot>Top-left</hotspot>
                        <wrapping>Word</wrapping>
                        <line-height>0</line-height>
                    </properties>
                    <blend-mode>0</blend-mode>
                    <effect-fallback>0</effect-fallback>
                    <world>
                        <x>99</x>
                        <y>1237</y>
                        <z>0</z>
                        <width>672</width>
                        <height>544</height>
                        <depth>0</depth>
                        <hotspotX>0</hotspotX>
                        <hotspotY>0</hotspotY>
                        <angle>0</angle>
                        <opacity>1</opacity>
                    </world>
                </instance>
                <instance type="DecayStartingValue" uid="104">
                    <properties>
                        <text>Decay Starting Value</text>
                        <initial-visibility>Visible</initial-visibility>
                        <font>Arial,-40,400,0</font>
                        <color>255,255,255</color>
                        <horizontal-alignment>Left</horizontal-alignment>
                        <vertical-alignment>Top</vertical-alignment>
                        <hotspot>Top-left</hotspot>
                        <wrapping>Word</wrapping>
                        <line-height>0</line-height>
                    </properties>
                    <blend-mode>0</blend-mode>
                    <effect-fallback>0</effect-fallback>
                    <world>
                        <x>2378</x>
                        <y>1299</y>
                        <z>0</z>
                        <width>558</width>
                        <height>472</height>
                        <depth>0</depth>
                        <hotspotX>0</hotspotX>
                        <hotspotY>0</hotspotY>
                        <angle>0</angle>
                        <opacity>1</opacity>
                    </world>
                </instance>
                <instance type="DepartureCushion" uid="39">
                    <properties>
                        <value>0.4</value>
                        <minimum>0</minimum>
                        <maximum>0.5</maximum>
                        <step>0.05</step>
                        <tooltip></tooltip>
                        <initial-visibility>Visible</initial-visibility>
                        <enabled>Yes</enabled>
                        <id-optional></id-optional>
                    </properties>
                    <blend-mode>0</blend-mode>
                    <effect-fallback>0</effect-fallback>
                    <world>
                        <x>-800</x>
                        <y>1568</y>
                        <z>0</z>
                        <width>200</width>
                        <height>25</height>
                        <depth>0</depth>
                        <hotspotX>0</hotspotX>
                        <hotspotY>0</hotspotY>
                    </world>
                </instance>
                <instance type="ArrivalCushion" uid="77">
                    <properties>
                        <value>0.6</value>
                        <minimum>0.5</minimum>
                        <maximum>1</maximum>
                        <step>0.05</step>
                        <tooltip></tooltip>
                        <initial-visibility>Visible</initial-visibility>
                        <enabled>Yes</enabled>
                        <id-optional></id-optional>
                    </properties>
                    <blend-mode>0</blend-mode>
                    <effect-fallback>0</effect-fallback>
                    <world>
                        <x>-1568</x>
                        <y>1376</y>
                        <z>0</z>
                        <width>200</width>
                        <height>25</height>
                        <depth>0</depth>
                        <hotspotX>0</hotspotX>
                        <hotspotY>0</hotspotY>
                    </world>
                </instance>
                <instance type="UpperCushion" uid="78">
                    <properties>
                        <text>Upper Cushion Bound</text>
                        <initial-visibility>Visible</initial-visibility>
                        <font>Arial,-32,400,0</font>
                        <color>255,255,255</color>
                        <horizontal-alignment>Left</horizontal-alignment>
                        <vertical-alignment>Top</vertical-alignment>
                        <hotspot>Top-left</hotspot>
                        <wrapping>Word</wrapping>
                        <line-height>0</line-height>
                    </properties>
                    <blend-mode>0</blend-mode>
                    <effect-fallback>0</effect-fallback>
                    <world>
                        <x>-1472</x>
                        <y>1248</y>
                        <z>0</z>
                        <width>512</width>
                        <height>512</height>
                        <depth>0</depth>
                        <hotspotX>0</hotspotX>
                        <hotspotY>0</hotspotY>
                        <angle>0</angle>
                        <opacity>1</opacity>
                    </world>
                </instance>
                <instance type="LowerCushion" uid="79">
                    <properties>
                        <text>Lower Cushion Bound</text>
                        <initial-visibility>Visible</initial-visibility>
                        <font>Arial,-32,400,0</font>
                        <color>255,255,255</color>
                        <horizontal-alignment>Left</horizontal-alignment>
                        <vertical-alignment>Top</vertical-alignment>
                        <hotspot>Top-left</hotspot>
                        <wrapping>Word</wrapping>
                        <line-height>0</line-height>
                    </properties>
                    <blend-mode>0</blend-mode>
                    <effect-fallback>0</effect-fallback>
                    <world>
                        <x>-672</x>
                        <y>1472</y>
                        <z>0</z>
                        <width>512</width>
                        <height>512</height>
                        <depth>0</depth>
                        <hotspotX>0</hotspotX>
                        <hotspotY>0</hotspotY>
                        <angle>0</angle>
                        <opacity>1</opacity>
                    </world>
                </instance>
            </instances>
            <effects />
        </layer>
        <layer name="Layer 1" sid="9971647631898102">
            <initially-visible>1</initially-visible>
            <background-color>255,255,255</background-color>
            <transparent>1</transparent>
            <parallax>
                <x>1</x>
                <y>1</y>
            </parallax>
            <zoom-rate>1</zoom-rate>
            <opacity>1</opacity>
            <force-own-texture>0</force-own-texture>
            <global>0</global>
            <use-render-cells>0</use-render-cells>
            <blend-mode>0</blend-mode>
            <effect-fallback>0</effect-fallback>
            <instances />
            <effects />
        </layer>
        <layer name="Layer 2" sid="2436965235802787">
            <initially-visible>1</initially-visible>
            <background-color>255,255,255</background-color>
            <transparent>1</transparent>
            <parallax>
                <x>1</x>
                <y>1</y>
            </parallax>
            <zoom-rate>1</zoom-rate>
            <opacity>1</opacity>
            <force-own-texture>0</force-own-texture>
            <global>0</global>
            <use-render-cells>0</use-render-cells>
            <blend-mode>0</blend-mode>
            <effect-fallback>0</effect-fallback>
            <instances>
                <instance type="Corners" uid="65">
                    <properties>
                        <initial-visibility>Visible</initial-visibility>
                        <initial-animation>Default</initial-animation>
                        <initial-frame>0</initial-frame>
                        <collisions>Enabled</collisions>
                    </properties>
                    <blend-mode>0</blend-mode>
                    <effect-fallback>0</effect-fallback>
                    <world>
                        <x>-63</x>
                        <y>-491</y>
                        <z>0</z>
                        <width>100</width>
                        <height>100</height>
                        <depth>0</depth>
                        <hotspotX>0.5</hotspotX>
                        <hotspotY>0.5</hotspotY>
                        <angle>0</angle>
                        <opacity>1</opacity>
                    </world>
                </instance>
            </instances>
            <effects />
        </layer>
    </layers>
    <nonworld-instances>
        <instance type="ArrayBuffer" uid="41">
            <properties>
                <width>10</width>
                <height>1</height>
                <depth>1</depth>
            </properties>
            <instance-variables>
                <Slot1>0</Slot1>
                <Slot2>0</Slot2>
                <Slot3>0</Slot3>
                <Slot4>0</Slot4>
            </instance-variables>
        </instance>
    </nonworld-instances>
    <effects />
</c2layout>
